{
  "generated_at": "2025-11-16T21:30:28.755Z",
  "total_organizations": 5,
  "total_bounties": 25,
  "total_value_usd": 2500,
  "version": "3.0.0",
  "organizations": {
    "triggerdotdev": {
      "display_name": "Triggerdotdev",
      "url": "https://algora.io/triggerdotdev/bounties?status=open",
      "bounty_count": 1,
      "total_value_usd": 100,
      "bounties": [
        {
          "id": "triggerdotdev#2654",
          "title": "Schema in object being inferred differently (and weirdly)",
          "amount_usd": 100,
          "url": "https://github.com/colinhacks/zod/issues/2654",
          "status": "open",
          "tags": [
            "go"
          ],
          "created_at": "2025-11-16T21:29:53.480Z",
          "updated_at": "2025-11-16T21:29:53.480Z"
        }
      ],
      "last_updated": "2025-11-16T21:30:28.755Z",
      "scrape_duration_ms": 0
    },
    "omnigres": {
      "display_name": "Omnigres",
      "url": "https://algora.io/omnigres/bounties?status=open",
      "bounty_count": 1,
      "total_value_usd": 100,
      "bounties": [
        {
          "id": "omnigres#823",
          "title": "Problem: omni_schema.dependency and omni_schema.acl views are slow",
          "amount_usd": 100,
          "url": "https://github.com/omnigres/omnigres/issues/823",
          "status": "open",
          "tags": [
            "go"
          ],
          "created_at": "2025-11-16T21:29:53.996Z",
          "updated_at": "2025-11-16T21:29:53.996Z"
        }
      ],
      "last_updated": "2025-11-16T21:30:28.755Z",
      "scrape_duration_ms": 0
    },
    "GolemCloud": {
      "display_name": "GolemCloud",
      "url": "https://algora.io/GolemCloud/bounties?status=open",
      "bounty_count": 3,
      "total_value_usd": 300,
      "bounties": [
        {
          "id": "GolemCloud#275",
          "title": "Incorporate MCP Server into Golem CLI",
          "amount_usd": 100,
          "url": "https://github.com/golemcloud/golem/issues/1926",
          "status": "open",
          "tags": [
            "go"
          ],
          "created_at": "2025-11-16T21:29:54.012Z",
          "updated_at": "2025-11-16T21:29:54.012Z"
        },
        {
          "id": "GolemCloud#23",
          "title": "Implement Durable Text-to-Speech Provider Components for golem:tts WIT Interface",
          "amount_usd": 100,
          "url": "https://github.com/golemcloud/golem-ai/issues/23",
          "status": "open",
          "tags": [
            "go"
          ],
          "created_at": "2025-11-16T21:29:54.906Z",
          "updated_at": "2025-11-16T21:29:54.906Z"
        },
        {
          "id": "GolemCloud#21",
          "title": "Implement Durable Vector Database Provider Components for golem:vector WIT Interface",
          "amount_usd": 100,
          "url": "https://github.com/golemcloud/golem-ai/issues/21",
          "status": "open",
          "tags": [
            "go"
          ],
          "created_at": "2025-11-16T21:29:56.430Z",
          "updated_at": "2025-11-16T21:29:56.430Z"
        }
      ],
      "last_updated": "2025-11-16T21:30:28.755Z",
      "scrape_duration_ms": 0
    },
    "mediar-ai": {
      "display_name": "Mediar-ai",
      "url": "https://algora.io/mediar-ai/bounties?status=open",
      "bounty_count": 10,
      "total_value_usd": 1000,
      "bounties": [
        {
          "id": "mediar-ai#357",
          "title": "create a TS workflow that delete the oldest version of PyPI before publishing to PyPI",
          "amount_usd": 100,
          "url": "https://github.com/mediar-ai/terminator/issues/357",
          "status": "open",
          "tags": [
            "go"
          ],
          "created_at": "2025-11-16T21:29:53.654Z",
          "updated_at": "2025-11-16T21:29:53.654Z"
        },
        {
          "id": "mediar-ai#353",
          "title": "create a typescript workflow that test the browser script bridge",
          "amount_usd": 100,
          "url": "https://github.com/mediar-ai/terminator/issues/353",
          "status": "open",
          "tags": [],
          "created_at": "2025-11-16T21:29:54.011Z",
          "updated_at": "2025-11-16T21:29:54.011Z"
        },
        {
          "id": "mediar-ai#352",
          "title": "increase success rate of browser extension workflow",
          "amount_usd": 100,
          "url": "https://github.com/mediar-ai/terminator/issues/352",
          "status": "open",
          "tags": [],
          "created_at": "2025-11-16T21:29:54.906Z",
          "updated_at": "2025-11-16T21:29:54.906Z"
        },
        {
          "id": "mediar-ai#315",
          "title": "[bounty] test and showcase the new gemini computer use model with terminator MCP",
          "amount_usd": 100,
          "url": "https://github.com/mediar-ai/terminator/issues/315",
          "status": "open",
          "tags": [],
          "created_at": "2025-11-16T21:29:56.481Z",
          "updated_at": "2025-11-16T21:29:56.481Z"
        },
        {
          "id": "mediar-ai#1626",
          "title": "[bounty] $400 fix audio device randomly stopping sometimes",
          "amount_usd": 100,
          "url": "https://github.com/mediar-ai/screenpipe/issues/1626",
          "status": "open",
          "tags": [],
          "created_at": "2025-11-16T21:29:59.921Z",
          "updated_at": "2025-11-16T21:29:59.921Z"
        },
        {
          "id": "mediar-ai#1560",
          "title": "[feature]  Implement Session Tracking for Application and Window Usage",
          "amount_usd": 100,
          "url": "https://github.com/mediar-ai/screenpipe/issues/1560",
          "status": "open",
          "tags": [],
          "created_at": "2025-11-16T21:30:02.238Z",
          "updated_at": "2025-11-16T21:30:02.238Z"
        },
        {
          "id": "mediar-ai#1441",
          "title": "[bounty] general purpose scrapper",
          "amount_usd": 100,
          "url": "https://github.com/mediar-ai/screenpipe/issues/1441",
          "status": "open",
          "tags": [],
          "created_at": "2025-11-16T21:30:04.876Z",
          "updated_at": "2025-11-16T21:30:04.876Z"
        },
        {
          "id": "mediar-ai#1298",
          "title": "[docs] document env var somewhere somehow ",
          "amount_usd": 100,
          "url": "https://github.com/mediar-ai/screenpipe/issues/1298",
          "status": "open",
          "tags": [],
          "created_at": "2025-11-16T21:30:06.218Z",
          "updated_at": "2025-11-16T21:30:06.218Z"
        },
        {
          "id": "mediar-ai#1383",
          "title": "[bounty] implement deep research in search pipe",
          "amount_usd": 100,
          "url": "https://github.com/mediar-ai/screenpipe/issues/1383",
          "status": "open",
          "tags": [],
          "created_at": "2025-11-16T21:30:07.837Z",
          "updated_at": "2025-11-16T21:30:07.837Z"
        },
        {
          "id": "mediar-ai#1382",
          "title": "[bounty] implement history for search pipe",
          "amount_usd": 100,
          "url": "https://github.com/mediar-ai/screenpipe/issues/1382",
          "status": "open",
          "tags": [],
          "created_at": "2025-11-16T21:30:08.651Z",
          "updated_at": "2025-11-16T21:30:08.651Z"
        }
      ],
      "last_updated": "2025-11-16T21:30:28.755Z",
      "scrape_duration_ms": 0
    },
    "zio": {
      "display_name": "Zio",
      "url": "https://algora.io/zio/bounties?status=open",
      "bounty_count": 10,
      "total_value_usd": 1000,
      "bounties": [
        {
          "id": "zio#3697",
          "title": "Datastar requests from Endpoint",
          "amount_usd": 100,
          "url": "https://github.com/zio/zio-http/issues/3697",
          "status": "open",
          "tags": [
            "go"
          ],
          "created_at": "2025-11-16T21:30:17.267Z",
          "updated_at": "2025-11-16T21:30:17.267Z"
        },
        {
          "id": "zio#709",
          "title": "Support Http Range header on request for Files",
          "amount_usd": 100,
          "url": "https://github.com/zio/zio-http/issues/709",
          "status": "open",
          "tags": [],
          "created_at": "2025-11-16T21:30:17.513Z",
          "updated_at": "2025-11-16T21:30:17.513Z"
        },
        {
          "id": "zio#3472",
          "title": "Split into multiple modules",
          "amount_usd": 100,
          "url": "https://github.com/zio/zio-http/issues/3472",
          "status": "open",
          "tags": [],
          "created_at": "2025-11-16T21:30:17.656Z",
          "updated_at": "2025-11-16T21:30:17.656Z"
        },
        {
          "id": "zio#9810",
          "title": "ZStreams buffer(1) is buffering 2.",
          "amount_usd": 100,
          "url": "https://github.com/zio/zio/issues/9810",
          "status": "open",
          "tags": [],
          "created_at": "2025-11-16T21:30:17.835Z",
          "updated_at": "2025-11-16T21:30:17.835Z"
        },
        {
          "id": "zio#9844",
          "title": "improved `Queue` shutdown functionality",
          "amount_usd": 100,
          "url": "https://github.com/zio/zio/issues/9844",
          "status": "open",
          "tags": [],
          "created_at": "2025-11-16T21:30:17.974Z",
          "updated_at": "2025-11-16T21:30:17.974Z"
        },
        {
          "id": "zio#9878",
          "title": "ZScheduler parks+unparks workers too frequently",
          "amount_usd": 100,
          "url": "https://github.com/zio/zio/issues/9878",
          "status": "open",
          "tags": [],
          "created_at": "2025-11-16T21:30:18.136Z",
          "updated_at": "2025-11-16T21:30:18.136Z"
        },
        {
          "id": "zio#9877",
          "title": "Can Fiber(Runtime) and Promise be merged?",
          "amount_usd": 100,
          "url": "https://github.com/zio/zio/issues/9877",
          "status": "open",
          "tags": [],
          "created_at": "2025-11-16T21:30:18.290Z",
          "updated_at": "2025-11-16T21:30:18.290Z"
        },
        {
          "id": "zio#9874",
          "title": "Handling errors allows recovering from defects",
          "amount_usd": 100,
          "url": "https://github.com/zio/zio/issues/9874",
          "status": "open",
          "tags": [],
          "created_at": "2025-11-16T21:30:18.453Z",
          "updated_at": "2025-11-16T21:30:18.453Z"
        },
        {
          "id": "zio#9681",
          "title": "Scala Native `WeakConcurrentBag` NPE when forking 10K fibers",
          "amount_usd": 100,
          "url": "https://github.com/zio/zio/issues/9681",
          "status": "open",
          "tags": [],
          "created_at": "2025-11-16T21:30:18.597Z",
          "updated_at": "2025-11-16T21:30:18.597Z"
        },
        {
          "id": "zio#9922",
          "title": "Add tests for `ZStreamAspect`",
          "amount_usd": 100,
          "url": "https://github.com/zio/zio/issues/9922",
          "status": "open",
          "tags": [],
          "created_at": "2025-11-16T21:30:18.753Z",
          "updated_at": "2025-11-16T21:30:18.753Z"
        }
      ],
      "last_updated": "2025-11-16T21:30:28.755Z",
      "scrape_duration_ms": 0
    }
  },
  "metadata": {
    "success_rate": 1,
    "processing_time_ms": 129106,
    "scraper_version": "unified-firecrawl-v1.0",
    "data_format": "legacy-compatible"
  },
  "stats": {
    "avg_bounty_value": 100,
    "median_bounty_value": 100,
    "top_organizations": [
      {
        "handle": "mediar-ai",
        "display_name": "Mediar-ai",
        "url": "https://algora.io/mediar-ai/bounties?status=open",
        "bounty_count": 10,
        "total_value_usd": 1000,
        "bounties": [
          {
            "id": "mediar-ai#357",
            "title": "create a TS workflow that delete the oldest version of PyPI before publishing to PyPI",
            "amount_usd": 100,
            "url": "https://github.com/mediar-ai/terminator/issues/357",
            "status": "open",
            "tags": [
              "go"
            ],
            "created_at": "2025-11-16T21:29:53.654Z",
            "updated_at": "2025-11-16T21:29:53.654Z"
          },
          {
            "id": "mediar-ai#353",
            "title": "create a typescript workflow that test the browser script bridge",
            "amount_usd": 100,
            "url": "https://github.com/mediar-ai/terminator/issues/353",
            "status": "open",
            "tags": [],
            "created_at": "2025-11-16T21:29:54.011Z",
            "updated_at": "2025-11-16T21:29:54.011Z"
          },
          {
            "id": "mediar-ai#352",
            "title": "increase success rate of browser extension workflow",
            "amount_usd": 100,
            "url": "https://github.com/mediar-ai/terminator/issues/352",
            "status": "open",
            "tags": [],
            "created_at": "2025-11-16T21:29:54.906Z",
            "updated_at": "2025-11-16T21:29:54.906Z"
          },
          {
            "id": "mediar-ai#315",
            "title": "[bounty] test and showcase the new gemini computer use model with terminator MCP",
            "amount_usd": 100,
            "url": "https://github.com/mediar-ai/terminator/issues/315",
            "status": "open",
            "tags": [],
            "created_at": "2025-11-16T21:29:56.481Z",
            "updated_at": "2025-11-16T21:29:56.481Z"
          },
          {
            "id": "mediar-ai#1626",
            "title": "[bounty] $400 fix audio device randomly stopping sometimes",
            "amount_usd": 100,
            "url": "https://github.com/mediar-ai/screenpipe/issues/1626",
            "status": "open",
            "tags": [],
            "created_at": "2025-11-16T21:29:59.921Z",
            "updated_at": "2025-11-16T21:29:59.921Z"
          },
          {
            "id": "mediar-ai#1560",
            "title": "[feature]  Implement Session Tracking for Application and Window Usage",
            "amount_usd": 100,
            "url": "https://github.com/mediar-ai/screenpipe/issues/1560",
            "status": "open",
            "tags": [],
            "created_at": "2025-11-16T21:30:02.238Z",
            "updated_at": "2025-11-16T21:30:02.238Z"
          },
          {
            "id": "mediar-ai#1441",
            "title": "[bounty] general purpose scrapper",
            "amount_usd": 100,
            "url": "https://github.com/mediar-ai/screenpipe/issues/1441",
            "status": "open",
            "tags": [],
            "created_at": "2025-11-16T21:30:04.876Z",
            "updated_at": "2025-11-16T21:30:04.876Z"
          },
          {
            "id": "mediar-ai#1298",
            "title": "[docs] document env var somewhere somehow ",
            "amount_usd": 100,
            "url": "https://github.com/mediar-ai/screenpipe/issues/1298",
            "status": "open",
            "tags": [],
            "created_at": "2025-11-16T21:30:06.218Z",
            "updated_at": "2025-11-16T21:30:06.218Z"
          },
          {
            "id": "mediar-ai#1383",
            "title": "[bounty] implement deep research in search pipe",
            "amount_usd": 100,
            "url": "https://github.com/mediar-ai/screenpipe/issues/1383",
            "status": "open",
            "tags": [],
            "created_at": "2025-11-16T21:30:07.837Z",
            "updated_at": "2025-11-16T21:30:07.837Z"
          },
          {
            "id": "mediar-ai#1382",
            "title": "[bounty] implement history for search pipe",
            "amount_usd": 100,
            "url": "https://github.com/mediar-ai/screenpipe/issues/1382",
            "status": "open",
            "tags": [],
            "created_at": "2025-11-16T21:30:08.651Z",
            "updated_at": "2025-11-16T21:30:08.651Z"
          }
        ],
        "last_updated": "2025-11-16T21:30:28.755Z",
        "scrape_duration_ms": 0
      },
      {
        "handle": "zio",
        "display_name": "Zio",
        "url": "https://algora.io/zio/bounties?status=open",
        "bounty_count": 10,
        "total_value_usd": 1000,
        "bounties": [
          {
            "id": "zio#3697",
            "title": "Datastar requests from Endpoint",
            "amount_usd": 100,
            "url": "https://github.com/zio/zio-http/issues/3697",
            "status": "open",
            "tags": [
              "go"
            ],
            "created_at": "2025-11-16T21:30:17.267Z",
            "updated_at": "2025-11-16T21:30:17.267Z"
          },
          {
            "id": "zio#709",
            "title": "Support Http Range header on request for Files",
            "amount_usd": 100,
            "url": "https://github.com/zio/zio-http/issues/709",
            "status": "open",
            "tags": [],
            "created_at": "2025-11-16T21:30:17.513Z",
            "updated_at": "2025-11-16T21:30:17.513Z"
          },
          {
            "id": "zio#3472",
            "title": "Split into multiple modules",
            "amount_usd": 100,
            "url": "https://github.com/zio/zio-http/issues/3472",
            "status": "open",
            "tags": [],
            "created_at": "2025-11-16T21:30:17.656Z",
            "updated_at": "2025-11-16T21:30:17.656Z"
          },
          {
            "id": "zio#9810",
            "title": "ZStreams buffer(1) is buffering 2.",
            "amount_usd": 100,
            "url": "https://github.com/zio/zio/issues/9810",
            "status": "open",
            "tags": [],
            "created_at": "2025-11-16T21:30:17.835Z",
            "updated_at": "2025-11-16T21:30:17.835Z"
          },
          {
            "id": "zio#9844",
            "title": "improved `Queue` shutdown functionality",
            "amount_usd": 100,
            "url": "https://github.com/zio/zio/issues/9844",
            "status": "open",
            "tags": [],
            "created_at": "2025-11-16T21:30:17.974Z",
            "updated_at": "2025-11-16T21:30:17.974Z"
          },
          {
            "id": "zio#9878",
            "title": "ZScheduler parks+unparks workers too frequently",
            "amount_usd": 100,
            "url": "https://github.com/zio/zio/issues/9878",
            "status": "open",
            "tags": [],
            "created_at": "2025-11-16T21:30:18.136Z",
            "updated_at": "2025-11-16T21:30:18.136Z"
          },
          {
            "id": "zio#9877",
            "title": "Can Fiber(Runtime) and Promise be merged?",
            "amount_usd": 100,
            "url": "https://github.com/zio/zio/issues/9877",
            "status": "open",
            "tags": [],
            "created_at": "2025-11-16T21:30:18.290Z",
            "updated_at": "2025-11-16T21:30:18.290Z"
          },
          {
            "id": "zio#9874",
            "title": "Handling errors allows recovering from defects",
            "amount_usd": 100,
            "url": "https://github.com/zio/zio/issues/9874",
            "status": "open",
            "tags": [],
            "created_at": "2025-11-16T21:30:18.453Z",
            "updated_at": "2025-11-16T21:30:18.453Z"
          },
          {
            "id": "zio#9681",
            "title": "Scala Native `WeakConcurrentBag` NPE when forking 10K fibers",
            "amount_usd": 100,
            "url": "https://github.com/zio/zio/issues/9681",
            "status": "open",
            "tags": [],
            "created_at": "2025-11-16T21:30:18.597Z",
            "updated_at": "2025-11-16T21:30:18.597Z"
          },
          {
            "id": "zio#9922",
            "title": "Add tests for `ZStreamAspect`",
            "amount_usd": 100,
            "url": "https://github.com/zio/zio/issues/9922",
            "status": "open",
            "tags": [],
            "created_at": "2025-11-16T21:30:18.753Z",
            "updated_at": "2025-11-16T21:30:18.753Z"
          }
        ],
        "last_updated": "2025-11-16T21:30:28.755Z",
        "scrape_duration_ms": 0
      },
      {
        "handle": "GolemCloud",
        "display_name": "GolemCloud",
        "url": "https://algora.io/GolemCloud/bounties?status=open",
        "bounty_count": 3,
        "total_value_usd": 300,
        "bounties": [
          {
            "id": "GolemCloud#275",
            "title": "Incorporate MCP Server into Golem CLI",
            "amount_usd": 100,
            "url": "https://github.com/golemcloud/golem/issues/1926",
            "status": "open",
            "tags": [
              "go"
            ],
            "created_at": "2025-11-16T21:29:54.012Z",
            "updated_at": "2025-11-16T21:29:54.012Z"
          },
          {
            "id": "GolemCloud#23",
            "title": "Implement Durable Text-to-Speech Provider Components for golem:tts WIT Interface",
            "amount_usd": 100,
            "url": "https://github.com/golemcloud/golem-ai/issues/23",
            "status": "open",
            "tags": [
              "go"
            ],
            "created_at": "2025-11-16T21:29:54.906Z",
            "updated_at": "2025-11-16T21:29:54.906Z"
          },
          {
            "id": "GolemCloud#21",
            "title": "Implement Durable Vector Database Provider Components for golem:vector WIT Interface",
            "amount_usd": 100,
            "url": "https://github.com/golemcloud/golem-ai/issues/21",
            "status": "open",
            "tags": [
              "go"
            ],
            "created_at": "2025-11-16T21:29:56.430Z",
            "updated_at": "2025-11-16T21:29:56.430Z"
          }
        ],
        "last_updated": "2025-11-16T21:30:28.755Z",
        "scrape_duration_ms": 0
      },
      {
        "handle": "triggerdotdev",
        "display_name": "Triggerdotdev",
        "url": "https://algora.io/triggerdotdev/bounties?status=open",
        "bounty_count": 1,
        "total_value_usd": 100,
        "bounties": [
          {
            "id": "triggerdotdev#2654",
            "title": "Schema in object being inferred differently (and weirdly)",
            "amount_usd": 100,
            "url": "https://github.com/colinhacks/zod/issues/2654",
            "status": "open",
            "tags": [
              "go"
            ],
            "created_at": "2025-11-16T21:29:53.480Z",
            "updated_at": "2025-11-16T21:29:53.480Z"
          }
        ],
        "last_updated": "2025-11-16T21:30:28.755Z",
        "scrape_duration_ms": 0
      },
      {
        "handle": "omnigres",
        "display_name": "Omnigres",
        "url": "https://algora.io/omnigres/bounties?status=open",
        "bounty_count": 1,
        "total_value_usd": 100,
        "bounties": [
          {
            "id": "omnigres#823",
            "title": "Problem: omni_schema.dependency and omni_schema.acl views are slow",
            "amount_usd": 100,
            "url": "https://github.com/omnigres/omnigres/issues/823",
            "status": "open",
            "tags": [
              "go"
            ],
            "created_at": "2025-11-16T21:29:53.996Z",
            "updated_at": "2025-11-16T21:29:53.996Z"
          }
        ],
        "last_updated": "2025-11-16T21:30:28.755Z",
        "scrape_duration_ms": 0
      }
    ]
  }
}