{
  "generated_at": "2025-12-31T23:51:33.426Z",
  "total_organizations": 3,
  "total_bounties": 4,
  "total_value_usd": 400,
  "version": "3.0.0",
  "organizations": {
    "triggerdotdev": {
      "display_name": "Triggerdotdev",
      "url": "https://algora.io/triggerdotdev/bounties?status=open",
      "bounty_count": 1,
      "total_value_usd": 100,
      "bounties": [
        {
          "id": "triggerdotdev#2654",
          "title": "Schema in object being inferred differently (and weirdly)",
          "amount_usd": 100,
          "url": "https://github.com/colinhacks/zod/issues/2654",
          "status": "open",
          "tags": [],
          "created_at": "2025-12-31T23:51:04.713Z",
          "updated_at": "2025-12-31T23:51:04.648Z"
        }
      ],
      "last_updated": "2025-12-31T23:51:33.426Z",
      "scrape_duration_ms": 0
    },
    "onyx-dot-app": {
      "display_name": "Onyx-dot-app",
      "url": "https://algora.io/onyx-dot-app/bounties?status=open",
      "bounty_count": 1,
      "total_value_usd": 100,
      "bounties": [
        {
          "id": "onyx-dot-app#2281",
          "title": "Jira Service Management Connector",
          "amount_usd": 100,
          "url": "https://github.com/onyx-dot-app/onyx/issues/2281",
          "status": "open",
          "tags": [],
          "created_at": "2025-12-31T23:51:04.862Z",
          "updated_at": "2025-12-31T23:51:04.862Z"
        }
      ],
      "last_updated": "2025-12-31T23:51:33.426Z",
      "scrape_duration_ms": 0
    },
    "outerbase": {
      "display_name": "Outerbase",
      "url": "https://algora.io/outerbase/bounties?status=open",
      "bounty_count": 2,
      "total_value_usd": 200,
      "bounties": [
        {
          "id": "outerbase#59",
          "title": "Database dumps do not work on large databases",
          "amount_usd": 100,
          "url": "https://github.com/outerbase/starbasedb/issues/59",
          "status": "open",
          "tags": [],
          "created_at": "2025-12-31T23:51:04.715Z",
          "updated_at": "2025-12-31T23:51:04.715Z"
        },
        {
          "id": "outerbase#72",
          "title": "Replicate data from external source to internal source with a Plugin",
          "amount_usd": 100,
          "url": "https://github.com/outerbase/starbasedb/issues/72",
          "status": "open",
          "tags": [],
          "created_at": "2025-12-31T23:51:04.903Z",
          "updated_at": "2025-12-31T23:51:04.903Z"
        }
      ],
      "last_updated": "2025-12-31T23:51:33.426Z",
      "scrape_duration_ms": 0
    }
  },
  "metadata": {
    "success_rate": 1,
    "processing_time_ms": 101048,
    "scraper_version": "unified-firecrawl-v1.0",
    "data_format": "legacy-compatible"
  },
  "stats": {
    "avg_bounty_value": 100,
    "median_bounty_value": 100,
    "top_organizations": [
      {
        "handle": "outerbase",
        "display_name": "Outerbase",
        "url": "https://algora.io/outerbase/bounties?status=open",
        "bounty_count": 2,
        "total_value_usd": 200,
        "bounties": [
          {
            "id": "outerbase#59",
            "title": "Database dumps do not work on large databases",
            "amount_usd": 100,
            "url": "https://github.com/outerbase/starbasedb/issues/59",
            "status": "open",
            "tags": [],
            "created_at": "2025-12-31T23:51:04.715Z",
            "updated_at": "2025-12-31T23:51:04.715Z"
          },
          {
            "id": "outerbase#72",
            "title": "Replicate data from external source to internal source with a Plugin",
            "amount_usd": 100,
            "url": "https://github.com/outerbase/starbasedb/issues/72",
            "status": "open",
            "tags": [],
            "created_at": "2025-12-31T23:51:04.903Z",
            "updated_at": "2025-12-31T23:51:04.903Z"
          }
        ],
        "last_updated": "2025-12-31T23:51:33.426Z",
        "scrape_duration_ms": 0
      },
      {
        "handle": "triggerdotdev",
        "display_name": "Triggerdotdev",
        "url": "https://algora.io/triggerdotdev/bounties?status=open",
        "bounty_count": 1,
        "total_value_usd": 100,
        "bounties": [
          {
            "id": "triggerdotdev#2654",
            "title": "Schema in object being inferred differently (and weirdly)",
            "amount_usd": 100,
            "url": "https://github.com/colinhacks/zod/issues/2654",
            "status": "open",
            "tags": [],
            "created_at": "2025-12-31T23:51:04.713Z",
            "updated_at": "2025-12-31T23:51:04.648Z"
          }
        ],
        "last_updated": "2025-12-31T23:51:33.426Z",
        "scrape_duration_ms": 0
      },
      {
        "handle": "onyx-dot-app",
        "display_name": "Onyx-dot-app",
        "url": "https://algora.io/onyx-dot-app/bounties?status=open",
        "bounty_count": 1,
        "total_value_usd": 100,
        "bounties": [
          {
            "id": "onyx-dot-app#2281",
            "title": "Jira Service Management Connector",
            "amount_usd": 100,
            "url": "https://github.com/onyx-dot-app/onyx/issues/2281",
            "status": "open",
            "tags": [],
            "created_at": "2025-12-31T23:51:04.862Z",
            "updated_at": "2025-12-31T23:51:04.862Z"
          }
        ],
        "last_updated": "2025-12-31T23:51:33.426Z",
        "scrape_duration_ms": 0
      }
    ]
  }
}