{
  "generated_at": "2025-11-19T20:16:06.636Z",
  "total_organizations": 12,
  "total_bounties": 76,
  "total_value_usd": 7600,
  "version": "3.0.0",
  "organizations": {
    "onyx-dot-app": {
      "display_name": "Onyx-dot-app",
      "url": "https://algora.io/onyx-dot-app/bounties?status=open",
      "bounty_count": 2,
      "total_value_usd": 200,
      "bounties": [
        {
          "id": "onyx-dot-app#2282",
          "title": "Github Pages Connector",
          "amount_usd": 100,
          "url": "https://github.com/onyx-dot-app/onyx/issues/2282",
          "status": "open",
          "tags": [
            "go"
          ],
          "created_at": "2025-11-19T20:15:17.635Z",
          "updated_at": "2025-11-19T20:15:17.635Z"
        },
        {
          "id": "onyx-dot-app#2281",
          "title": "Jira Service Management Connector",
          "amount_usd": 100,
          "url": "https://github.com/onyx-dot-app/onyx/issues/2281",
          "status": "open",
          "tags": [],
          "created_at": "2025-11-19T20:15:17.912Z",
          "updated_at": "2025-11-19T20:15:17.912Z"
        }
      ],
      "last_updated": "2025-11-19T20:16:06.635Z",
      "scrape_duration_ms": 0
    },
    "mudlet": {
      "display_name": "Mudlet",
      "url": "https://algora.io/mudlet/bounties?status=open",
      "bounty_count": 6,
      "total_value_usd": 600,
      "bounties": [
        {
          "id": "mudlet#8030",
          "title": "Split Mudlet up into `libmudlet` and a Qt front-end",
          "amount_usd": 100,
          "url": "https://github.com/Mudlet/Mudlet/issues/8030",
          "status": "open",
          "tags": [
            "go"
          ],
          "created_at": "2025-11-19T20:15:17.762Z",
          "updated_at": "2025-11-19T20:15:17.762Z"
        },
        {
          "id": "mudlet#3172",
          "title": "generic mapper: add video walkthrough on how to set it up",
          "amount_usd": 100,
          "url": "https://github.com/Mudlet/Mudlet/issues/3172",
          "status": "open",
          "tags": [
            "go"
          ],
          "created_at": "2025-11-19T20:15:17.951Z",
          "updated_at": "2025-11-19T20:15:17.951Z"
        },
        {
          "id": "mudlet#7126",
          "title": "Implement sentry.io's Qt SDK for crash reporting",
          "amount_usd": 100,
          "url": "https://github.com/Mudlet/Mudlet/issues/7126",
          "status": "open",
          "tags": [],
          "created_at": "2025-11-19T20:15:18.099Z",
          "updated_at": "2025-11-19T20:15:18.099Z"
        },
        {
          "id": "mudlet#689",
          "title": "Support telnet:// links",
          "amount_usd": 100,
          "url": "https://github.com/Mudlet/Mudlet/issues/689",
          "status": "open",
          "tags": [],
          "created_at": "2025-11-19T20:15:18.252Z",
          "updated_at": "2025-11-19T20:15:18.252Z"
        },
        {
          "id": "mudlet#707",
          "title": "Undo/redo support in editor",
          "amount_usd": 100,
          "url": "https://github.com/Mudlet/Mudlet/issues/707",
          "status": "open",
          "tags": [],
          "created_at": "2025-11-19T20:15:18.445Z",
          "updated_at": "2025-11-19T20:15:18.445Z"
        },
        {
          "id": "mudlet#5310",
          "title": "Autocomplete steals window focus, prevents further typing",
          "amount_usd": 100,
          "url": "https://github.com/Mudlet/Mudlet/issues/5310",
          "status": "open",
          "tags": [],
          "created_at": "2025-11-19T20:15:18.619Z",
          "updated_at": "2025-11-19T20:15:18.619Z"
        }
      ],
      "last_updated": "2025-11-19T20:16:06.635Z",
      "scrape_duration_ms": 0
    },
    "ZIO": {
      "display_name": "ZIO",
      "url": "https://algora.io/ZIO/bounties?status=open",
      "bounty_count": 10,
      "total_value_usd": 1000,
      "bounties": [
        {
          "id": "ZIO#3789",
          "title": "Server option to auto generate HEAD routes",
          "amount_usd": 100,
          "url": "https://github.com/zio/zio-http/issues/3789",
          "status": "open",
          "tags": [
            "go"
          ],
          "created_at": "2025-11-19T20:15:17.508Z",
          "updated_at": "2025-11-19T20:15:17.508Z"
        },
        {
          "id": "ZIO#3792",
          "title": "`DatastarEvent` handler for low-level API",
          "amount_usd": 100,
          "url": "https://github.com/zio/zio-http/issues/3792",
          "status": "open",
          "tags": [
            "go"
          ],
          "created_at": "2025-11-19T20:15:17.639Z",
          "updated_at": "2025-11-19T20:15:17.639Z"
        },
        {
          "id": "ZIO#3791",
          "title": "Read signals from query params to case class",
          "amount_usd": 100,
          "url": "https://github.com/zio/zio-http/issues/3791",
          "status": "open",
          "tags": [],
          "created_at": "2025-11-19T20:15:17.792Z",
          "updated_at": "2025-11-19T20:15:17.792Z"
        },
        {
          "id": "ZIO#3793",
          "title": "Datastar migration for 1.0.0 RC6",
          "amount_usd": 100,
          "url": "https://github.com/zio/zio-http/issues/3793",
          "status": "open",
          "tags": [],
          "created_at": "2025-11-19T20:15:17.993Z",
          "updated_at": "2025-11-19T20:15:17.993Z"
        },
        {
          "id": "ZIO#3794",
          "title": "Add constructors for CDN script elements and templates for datastart SSR pages",
          "amount_usd": 100,
          "url": "https://github.com/zio/zio-http/issues/3794",
          "status": "open",
          "tags": [],
          "created_at": "2025-11-19T20:15:18.252Z",
          "updated_at": "2025-11-19T20:15:18.252Z"
        },
        {
          "id": "ZIO#3779",
          "title": "Fix bug in JS HTTP Client not reading full response body",
          "amount_usd": 100,
          "url": "https://github.com/zio/zio-http/issues/3779",
          "status": "open",
          "tags": [],
          "created_at": "2025-11-19T20:15:18.405Z",
          "updated_at": "2025-11-19T20:15:18.405Z"
        },
        {
          "id": "ZIO#3697",
          "title": "Datastar requests from Endpoint",
          "amount_usd": 100,
          "url": "https://github.com/zio/zio-http/issues/3697",
          "status": "open",
          "tags": [],
          "created_at": "2025-11-19T20:15:18.559Z",
          "updated_at": "2025-11-19T20:15:18.559Z"
        },
        {
          "id": "ZIO#709",
          "title": "Support Http Range header on request for Files",
          "amount_usd": 100,
          "url": "https://github.com/zio/zio-http/issues/709",
          "status": "open",
          "tags": [],
          "created_at": "2025-11-19T20:15:18.691Z",
          "updated_at": "2025-11-19T20:15:18.691Z"
        },
        {
          "id": "ZIO#3472",
          "title": "Split into multiple modules",
          "amount_usd": 100,
          "url": "https://github.com/zio/zio-http/issues/3472",
          "status": "open",
          "tags": [],
          "created_at": "2025-11-19T20:15:18.903Z",
          "updated_at": "2025-11-19T20:15:18.903Z"
        },
        {
          "id": "ZIO#9810",
          "title": "ZStreams buffer(1) is buffering 2.",
          "amount_usd": 100,
          "url": "https://github.com/zio/zio/issues/9810",
          "status": "open",
          "tags": [],
          "created_at": "2025-11-19T20:15:19.047Z",
          "updated_at": "2025-11-19T20:15:19.047Z"
        }
      ],
      "last_updated": "2025-11-19T20:16:06.635Z",
      "scrape_duration_ms": 0
    },
    "tscircuit": {
      "display_name": "Tscircuit",
      "url": "https://algora.io/tscircuit/bounties?status=open",
      "bounty_count": 10,
      "total_value_usd": 1000,
      "bounties": [
        {
          "id": "tscircuit#1130",
          "title": "Change of color on hover for traces are missing",
          "amount_usd": 100,
          "url": "https://github.com/tscircuit/tscircuit/issues/1130",
          "status": "open",
          "tags": [
            "go"
          ],
          "created_at": "2025-11-19T20:15:17.670Z",
          "updated_at": "2025-11-19T20:15:17.670Z"
        },
        {
          "id": "tscircuit#83",
          "title": "In the case of multiple overlaps on a parallel line, choose to offset to minimize crossings",
          "amount_usd": 100,
          "url": "https://github.com/tscircuit/schematic-trace-solver/issues/83",
          "status": "open",
          "tags": [],
          "created_at": "2025-11-19T20:15:17.850Z",
          "updated_at": "2025-11-19T20:15:17.850Z"
        },
        {
          "id": "tscircuit#534",
          "title": "Texture Support (PCB should have texture on box)",
          "amount_usd": 100,
          "url": "https://github.com/tscircuit/3d-viewer/issues/534",
          "status": "open",
          "tags": [],
          "created_at": "2025-11-19T20:15:18.073Z",
          "updated_at": "2025-11-19T20:15:18.073Z"
        },
        {
          "id": "tscircuit#419",
          "title": "Texture Support (PCB should have texture on box)",
          "amount_usd": 100,
          "url": "https://github.com/tscircuit/3d-viewer/issues/534",
          "status": "open",
          "tags": [],
          "created_at": "2025-11-19T20:15:18.181Z",
          "updated_at": "2025-11-19T20:15:18.181Z"
        },
        {
          "id": "tscircuit#1081",
          "title": "Make sure kicad component components create courtyards",
          "amount_usd": 100,
          "url": "https://github.com/tscircuit/tscircuit/issues/1081",
          "status": "open",
          "tags": [],
          "created_at": "2025-11-19T20:15:18.380Z",
          "updated_at": "2025-11-19T20:15:18.380Z"
        },
        {
          "id": "tscircuit#386",
          "title": "Add support for qfn32",
          "amount_usd": 100,
          "url": "https://github.com/tscircuit/jscad-electronics/issues/139",
          "status": "open",
          "tags": [],
          "created_at": "2025-11-19T20:15:18.683Z",
          "updated_at": "2025-11-19T20:15:18.683Z"
        },
        {
          "id": "tscircuit#1498",
          "title": "Bug schematic traces with the same net name jumpeing to eachother ",
          "amount_usd": 100,
          "url": "https://github.com/tscircuit/core/issues/1498",
          "status": "open",
          "tags": [],
          "created_at": "2025-11-19T20:15:18.856Z",
          "updated_at": "2025-11-19T20:15:18.856Z"
        },
        {
          "id": "tscircuit#79",
          "title": "Fix extra net label in repro61, or remove trace",
          "amount_usd": 100,
          "url": "https://github.com/tscircuit/schematic-trace-solver/issues/79",
          "status": "open",
          "tags": [],
          "created_at": "2025-11-19T20:15:19.017Z",
          "updated_at": "2025-11-19T20:15:19.017Z"
        },
        {
          "id": "tscircuit#78",
          "title": "Fix extra trace lines in post-processing step",
          "amount_usd": 100,
          "url": "https://github.com/tscircuit/schematic-trace-solver/issues/78",
          "status": "open",
          "tags": [],
          "created_at": "2025-11-19T20:15:19.150Z",
          "updated_at": "2025-11-19T20:15:19.150Z"
        },
        {
          "id": "tscircuit#176",
          "title": "Proposal: Add SparkFun MicroMod STM32 Processor (STM32F405)",
          "amount_usd": 100,
          "url": "https://github.com/tscircuit/sparkfun-boards/issues/176",
          "status": "open",
          "tags": [],
          "created_at": "2025-11-19T20:15:19.312Z",
          "updated_at": "2025-11-19T20:15:19.312Z"
        }
      ],
      "last_updated": "2025-11-19T20:16:06.636Z",
      "scrape_duration_ms": 0
    },
    "cal": {
      "display_name": "Cal",
      "url": "https://algora.io/cal/bounties?status=open",
      "bounty_count": 10,
      "total_value_usd": 1000,
      "bounties": [
        {
          "id": "cal#23104",
          "title": "Local dev crazy slow",
          "amount_usd": 100,
          "url": "https://github.com/calcom/cal.com/issues/23104",
          "status": "open",
          "tags": [
            "go"
          ],
          "created_at": "2025-11-19T20:15:20.802Z",
          "updated_at": "2025-11-19T20:15:20.802Z"
        },
        {
          "id": "cal#9485",
          "title": "CalDAV integration with Fastmail is generating duplicate, erroneous invitation emails.",
          "amount_usd": 100,
          "url": "https://github.com/calcom/cal.com/issues/9485",
          "status": "open",
          "tags": [],
          "created_at": "2025-11-19T20:15:20.990Z",
          "updated_at": "2025-11-19T20:15:20.990Z"
        },
        {
          "id": "cal#18947",
          "title": "[CAL-5091] additional settings: \"add team member as optional guest",
          "amount_usd": 100,
          "url": "https://github.com/calcom/cal.com/issues/18947",
          "status": "open",
          "tags": [],
          "created_at": "2025-11-19T20:15:21.144Z",
          "updated_at": "2025-11-19T20:15:21.144Z"
        },
        {
          "id": "cal#18992",
          "title": "[CAL-5107] add no-show to zapier (its a webhook only right now)",
          "amount_usd": 100,
          "url": "https://github.com/calcom/cal.com/issues/18992",
          "status": "open",
          "tags": [],
          "created_at": "2025-11-19T20:15:21.284Z",
          "updated_at": "2025-11-19T20:15:21.284Z"
        },
        {
          "id": "cal#18987",
          "title": "[CAL-5097] add the same \"booking questions\" to routing forms",
          "amount_usd": 100,
          "url": "https://github.com/calcom/cal.com/issues/18987",
          "status": "open",
          "tags": [],
          "created_at": "2025-11-19T20:15:21.433Z",
          "updated_at": "2025-11-19T20:15:21.433Z"
        },
        {
          "id": "cal#16797",
          "title": "Native Pipedrive integration",
          "amount_usd": 100,
          "url": "https://github.com/calcom/cal.com/issues/16797",
          "status": "open",
          "tags": [],
          "created_at": "2025-11-19T20:15:21.590Z",
          "updated_at": "2025-11-19T20:15:21.590Z"
        },
        {
          "id": "cal#16651",
          "title": "[CAL-4716] Missing Notifications for Events",
          "amount_usd": 100,
          "url": "https://github.com/calcom/cal.com/issues/16651",
          "status": "open",
          "tags": [],
          "created_at": "2025-11-19T20:15:21.730Z",
          "updated_at": "2025-11-19T20:15:21.730Z"
        },
        {
          "id": "cal#8123",
          "title": "[CAL-1425] Exchange on Premise 2016",
          "amount_usd": 100,
          "url": "https://github.com/calcom/cal.com/issues/8123",
          "status": "open",
          "tags": [],
          "created_at": "2025-11-19T20:15:21.916Z",
          "updated_at": "2025-11-19T20:15:21.916Z"
        },
        {
          "id": "cal#16378",
          "title": "[CAL-4531] Take into account guest's availability when rescheduling",
          "amount_usd": 100,
          "url": "https://github.com/calcom/cal.com/issues/16378",
          "status": "open",
          "tags": [],
          "created_at": "2025-11-19T20:15:22.087Z",
          "updated_at": "2025-11-19T20:15:22.087Z"
        },
        {
          "id": "cal#13532",
          "title": "[CAL-3076] allow emails and invite people to a team event-type directly from \"assignment\" if not in team yet",
          "amount_usd": 100,
          "url": "https://github.com/calcom/cal.com/issues/13532",
          "status": "open",
          "tags": [],
          "created_at": "2025-11-19T20:15:22.266Z",
          "updated_at": "2025-11-19T20:15:22.266Z"
        }
      ],
      "last_updated": "2025-11-19T20:16:06.636Z",
      "scrape_duration_ms": 0
    },
    "keephq": {
      "display_name": "Keephq",
      "url": "https://algora.io/keephq/bounties?status=open",
      "bounty_count": 5,
      "total_value_usd": 500,
      "bounties": [
        {
          "id": "keephq#3960",
          "title": "[🔌 Provider]: Nagios Provider",
          "amount_usd": 100,
          "url": "https://github.com/keephq/keep/issues/3960",
          "status": "open",
          "tags": [
            "go"
          ],
          "created_at": "2025-11-19T20:15:28.482Z",
          "updated_at": "2025-11-19T20:15:28.482Z"
        },
        {
          "id": "keephq#3526",
          "title": "[🔌 Provider]: Solarwinds",
          "amount_usd": 100,
          "url": "https://github.com/keephq/keep/issues/3526",
          "status": "open",
          "tags": [],
          "created_at": "2025-11-19T20:15:28.643Z",
          "updated_at": "2025-11-19T20:15:28.643Z"
        },
        {
          "id": "keephq#3376",
          "title": "[➕ Feature]: Add a way to validate Keep workflows from CI",
          "amount_usd": 100,
          "url": "https://github.com/keephq/keep/issues/3376",
          "status": "open",
          "tags": [],
          "created_at": "2025-11-19T20:15:28.773Z",
          "updated_at": "2025-11-19T20:15:28.773Z"
        },
        {
          "id": "keephq#3379",
          "title": "[🔌 Provider]: ServiceNow pull activity from incidents into incidents",
          "amount_usd": 100,
          "url": "https://github.com/keephq/keep/issues/3379",
          "status": "open",
          "tags": [],
          "created_at": "2025-11-19T20:15:28.900Z",
          "updated_at": "2025-11-19T20:15:28.900Z"
        },
        {
          "id": "keephq#2112",
          "title": "[🔌 Provider]: SNMP provider",
          "amount_usd": 100,
          "url": "https://github.com/keephq/keep/issues/2112",
          "status": "open",
          "tags": [],
          "created_at": "2025-11-19T20:15:29.069Z",
          "updated_at": "2025-11-19T20:15:29.069Z"
        }
      ],
      "last_updated": "2025-11-19T20:16:06.636Z",
      "scrape_duration_ms": 0
    },
    "zio": {
      "display_name": "Zio",
      "url": "https://algora.io/zio/bounties?status=open",
      "bounty_count": 10,
      "total_value_usd": 1000,
      "bounties": [
        {
          "id": "zio#3789",
          "title": "Server option to auto generate HEAD routes",
          "amount_usd": 100,
          "url": "https://github.com/zio/zio-http/issues/3789",
          "status": "open",
          "tags": [
            "go"
          ],
          "created_at": "2025-11-19T20:15:30.866Z",
          "updated_at": "2025-11-19T20:15:30.866Z"
        },
        {
          "id": "zio#3792",
          "title": "`DatastarEvent` handler for low-level API",
          "amount_usd": 100,
          "url": "https://github.com/zio/zio-http/issues/3792",
          "status": "open",
          "tags": [
            "go"
          ],
          "created_at": "2025-11-19T20:15:30.891Z",
          "updated_at": "2025-11-19T20:15:30.891Z"
        },
        {
          "id": "zio#3791",
          "title": "Read signals from query params to case class",
          "amount_usd": 100,
          "url": "https://github.com/zio/zio-http/issues/3791",
          "status": "open",
          "tags": [],
          "created_at": "2025-11-19T20:15:30.915Z",
          "updated_at": "2025-11-19T20:15:30.915Z"
        },
        {
          "id": "zio#3793",
          "title": "Datastar migration for 1.0.0 RC6",
          "amount_usd": 100,
          "url": "https://github.com/zio/zio-http/issues/3793",
          "status": "open",
          "tags": [],
          "created_at": "2025-11-19T20:15:30.940Z",
          "updated_at": "2025-11-19T20:15:30.940Z"
        },
        {
          "id": "zio#3794",
          "title": "Add constructors for CDN script elements and templates for datastart SSR pages",
          "amount_usd": 100,
          "url": "https://github.com/zio/zio-http/issues/3794",
          "status": "open",
          "tags": [],
          "created_at": "2025-11-19T20:15:30.965Z",
          "updated_at": "2025-11-19T20:15:30.965Z"
        },
        {
          "id": "zio#3779",
          "title": "Fix bug in JS HTTP Client not reading full response body",
          "amount_usd": 100,
          "url": "https://github.com/zio/zio-http/issues/3779",
          "status": "open",
          "tags": [],
          "created_at": "2025-11-19T20:15:30.990Z",
          "updated_at": "2025-11-19T20:15:30.990Z"
        },
        {
          "id": "zio#3697",
          "title": "Datastar requests from Endpoint",
          "amount_usd": 100,
          "url": "https://github.com/zio/zio-http/issues/3697",
          "status": "open",
          "tags": [],
          "created_at": "2025-11-19T20:15:31.014Z",
          "updated_at": "2025-11-19T20:15:31.014Z"
        },
        {
          "id": "zio#709",
          "title": "Support Http Range header on request for Files",
          "amount_usd": 100,
          "url": "https://github.com/zio/zio-http/issues/709",
          "status": "open",
          "tags": [],
          "created_at": "2025-11-19T20:15:31.039Z",
          "updated_at": "2025-11-19T20:15:31.039Z"
        },
        {
          "id": "zio#3472",
          "title": "Split into multiple modules",
          "amount_usd": 100,
          "url": "https://github.com/zio/zio-http/issues/3472",
          "status": "open",
          "tags": [],
          "created_at": "2025-11-19T20:15:31.064Z",
          "updated_at": "2025-11-19T20:15:31.064Z"
        },
        {
          "id": "zio#9810",
          "title": "ZStreams buffer(1) is buffering 2.",
          "amount_usd": 100,
          "url": "https://github.com/zio/zio/issues/9810",
          "status": "open",
          "tags": [],
          "created_at": "2025-11-19T20:15:31.089Z",
          "updated_at": "2025-11-19T20:15:31.089Z"
        }
      ],
      "last_updated": "2025-11-19T20:16:06.636Z",
      "scrape_duration_ms": 0
    },
    "activepieces": {
      "display_name": "Activepieces",
      "url": "https://algora.io/activepieces/bounties?status=open",
      "bounty_count": 5,
      "total_value_usd": 500,
      "bounties": [
        {
          "id": "activepieces#9703",
          "title": "Issue #9703",
          "amount_usd": 100,
          "url": "github.com/activepieces/activepieces/issues/9703",
          "status": "open",
          "tags": [
            "go"
          ],
          "created_at": "2025-11-19T20:15:31.290Z",
          "updated_at": "2025-11-19T20:15:31.290Z"
        },
        {
          "id": "activepieces#8284",
          "title": "Issue #8284",
          "amount_usd": 100,
          "url": "github.com/activepieces/activepieces/issues/8284",
          "status": "open",
          "tags": [
            "go"
          ],
          "created_at": "2025-11-19T20:15:31.314Z",
          "updated_at": "2025-11-19T20:15:31.314Z"
        },
        {
          "id": "activepieces#8135",
          "title": "Issue #8135",
          "amount_usd": 100,
          "url": "github.com/activepieces/activepieces/issues/8135",
          "status": "open",
          "tags": [],
          "created_at": "2025-11-19T20:15:31.339Z",
          "updated_at": "2025-11-19T20:15:31.339Z"
        },
        {
          "id": "activepieces#8135",
          "title": "Issue #8135",
          "amount_usd": 100,
          "url": "github.com/activepieces/activepieces/issues/8135",
          "status": "open",
          "tags": [],
          "created_at": "2025-11-19T20:15:31.363Z",
          "updated_at": "2025-11-19T20:15:31.363Z"
        },
        {
          "id": "activepieces#8072",
          "title": "Issue #8072",
          "amount_usd": 100,
          "url": "github.com/activepieces/activepieces/issues/8072",
          "status": "open",
          "tags": [],
          "created_at": "2025-11-19T20:15:31.387Z",
          "updated_at": "2025-11-19T20:15:31.387Z"
        }
      ],
      "last_updated": "2025-11-19T20:16:06.636Z",
      "scrape_duration_ms": 0
    },
    "Mudlet": {
      "display_name": "Mudlet",
      "url": "https://algora.io/Mudlet/bounties?status=open",
      "bounty_count": 6,
      "total_value_usd": 600,
      "bounties": [
        {
          "id": "Mudlet#8030",
          "title": "Issue #8030",
          "amount_usd": 100,
          "url": "github.com/Mudlet/Mudlet/issues/8030",
          "status": "open",
          "tags": [
            "go"
          ],
          "created_at": "2025-11-19T20:15:34.852Z",
          "updated_at": "2025-11-19T20:15:34.852Z"
        },
        {
          "id": "Mudlet#3172",
          "title": "Issue #3172",
          "amount_usd": 100,
          "url": "github.com/Mudlet/Mudlet/issues/3172",
          "status": "open",
          "tags": [
            "go"
          ],
          "created_at": "2025-11-19T20:15:34.876Z",
          "updated_at": "2025-11-19T20:15:34.876Z"
        },
        {
          "id": "Mudlet#7126",
          "title": "Issue #7126",
          "amount_usd": 100,
          "url": "github.com/Mudlet/Mudlet/issues/7126",
          "status": "open",
          "tags": [],
          "created_at": "2025-11-19T20:15:34.900Z",
          "updated_at": "2025-11-19T20:15:34.900Z"
        },
        {
          "id": "Mudlet#689",
          "title": "Issue #689",
          "amount_usd": 100,
          "url": "github.com/Mudlet/Mudlet/issues/689",
          "status": "open",
          "tags": [],
          "created_at": "2025-11-19T20:15:34.925Z",
          "updated_at": "2025-11-19T20:15:34.925Z"
        },
        {
          "id": "Mudlet#707",
          "title": "Issue #707",
          "amount_usd": 100,
          "url": "github.com/Mudlet/Mudlet/issues/707",
          "status": "open",
          "tags": [],
          "created_at": "2025-11-19T20:15:34.949Z",
          "updated_at": "2025-11-19T20:15:34.949Z"
        },
        {
          "id": "Mudlet#5310",
          "title": "Issue #5310",
          "amount_usd": 100,
          "url": "github.com/Mudlet/Mudlet/issues/5310",
          "status": "open",
          "tags": [],
          "created_at": "2025-11-19T20:15:34.974Z",
          "updated_at": "2025-11-19T20:15:34.974Z"
        }
      ],
      "last_updated": "2025-11-19T20:16:06.636Z",
      "scrape_duration_ms": 0
    },
    "omnigres": {
      "display_name": "Omnigres",
      "url": "https://algora.io/omnigres/bounties?status=open",
      "bounty_count": 1,
      "total_value_usd": 100,
      "bounties": [
        {
          "id": "omnigres#823",
          "title": "Issue #823",
          "amount_usd": 100,
          "url": "github.com/omnigres/omnigres/issues/823",
          "status": "open",
          "tags": [
            "go"
          ],
          "created_at": "2025-11-19T20:15:56.490Z",
          "updated_at": "2025-11-19T20:15:56.490Z"
        }
      ],
      "last_updated": "2025-11-19T20:16:06.636Z",
      "scrape_duration_ms": 0
    },
    "projectdiscovery": {
      "display_name": "Projectdiscovery",
      "url": "https://algora.io/projectdiscovery/bounties?status=open",
      "bounty_count": 8,
      "total_value_usd": 800,
      "bounties": [
        {
          "id": "projectdiscovery#13942",
          "title": "Issue #13942",
          "amount_usd": 100,
          "url": "github.com/projectdiscovery/nuclei-templates/issues/13942",
          "status": "open",
          "tags": [
            "go"
          ],
          "created_at": "2025-11-19T20:15:56.363Z",
          "updated_at": "2025-11-19T20:15:56.363Z"
        },
        {
          "id": "projectdiscovery#13942",
          "title": "Issue #13942",
          "amount_usd": 100,
          "url": "github.com/projectdiscovery/nuclei-templates/issues/13942",
          "status": "open",
          "tags": [
            "go"
          ],
          "created_at": "2025-11-19T20:15:56.387Z",
          "updated_at": "2025-11-19T20:15:56.387Z"
        },
        {
          "id": "projectdiscovery#13933",
          "title": "Issue #13933",
          "amount_usd": 100,
          "url": "github.com/projectdiscovery/nuclei-templates/issues/13933",
          "status": "open",
          "tags": [],
          "created_at": "2025-11-19T20:15:56.411Z",
          "updated_at": "2025-11-19T20:15:56.411Z"
        },
        {
          "id": "projectdiscovery#13923",
          "title": "Issue #13923",
          "amount_usd": 100,
          "url": "github.com/projectdiscovery/nuclei-templates/issues/13923",
          "status": "open",
          "tags": [],
          "created_at": "2025-11-19T20:15:56.442Z",
          "updated_at": "2025-11-19T20:15:56.442Z"
        },
        {
          "id": "projectdiscovery#13915",
          "title": "Issue #13915",
          "amount_usd": 100,
          "url": "github.com/projectdiscovery/nuclei-templates/issues/13915",
          "status": "open",
          "tags": [],
          "created_at": "2025-11-19T20:15:56.466Z",
          "updated_at": "2025-11-19T20:15:56.466Z"
        },
        {
          "id": "projectdiscovery#13886",
          "title": "Issue #13886",
          "amount_usd": 100,
          "url": "github.com/projectdiscovery/nuclei-templates/issues/13886",
          "status": "open",
          "tags": [],
          "created_at": "2025-11-19T20:15:56.514Z",
          "updated_at": "2025-11-19T20:15:56.514Z"
        },
        {
          "id": "projectdiscovery#13820",
          "title": "Issue #13820",
          "amount_usd": 100,
          "url": "github.com/projectdiscovery/nuclei-templates/issues/13820",
          "status": "open",
          "tags": [],
          "created_at": "2025-11-19T20:15:56.538Z",
          "updated_at": "2025-11-19T20:15:56.538Z"
        },
        {
          "id": "projectdiscovery#13724",
          "title": "Issue #13724",
          "amount_usd": 100,
          "url": "github.com/projectdiscovery/nuclei-templates/issues/13724",
          "status": "open",
          "tags": [],
          "created_at": "2025-11-19T20:15:56.586Z",
          "updated_at": "2025-11-19T20:15:56.586Z"
        }
      ],
      "last_updated": "2025-11-19T20:16:06.636Z",
      "scrape_duration_ms": 0
    },
    "qdrant": {
      "display_name": "Qdrant",
      "url": "https://algora.io/qdrant/bounties?status=open",
      "bounty_count": 3,
      "total_value_usd": 300,
      "bounties": [
        {
          "id": "qdrant#3531",
          "title": "Issue #3531",
          "amount_usd": 100,
          "url": "github.com/qdrant/qdrant/issues/3531",
          "status": "open",
          "tags": [
            "go"
          ],
          "created_at": "2025-11-19T20:15:56.562Z",
          "updated_at": "2025-11-19T20:15:56.562Z"
        },
        {
          "id": "qdrant#3322",
          "title": "Issue #3322",
          "amount_usd": 100,
          "url": "github.com/qdrant/qdrant/issues/3322",
          "status": "open",
          "tags": [],
          "created_at": "2025-11-19T20:15:56.609Z",
          "updated_at": "2025-11-19T20:15:56.609Z"
        },
        {
          "id": "qdrant#3321",
          "title": "Issue #3321",
          "amount_usd": 100,
          "url": "github.com/qdrant/qdrant/issues/3321",
          "status": "open",
          "tags": [],
          "created_at": "2025-11-19T20:15:56.634Z",
          "updated_at": "2025-11-19T20:15:56.634Z"
        }
      ],
      "last_updated": "2025-11-19T20:16:06.636Z",
      "scrape_duration_ms": 0
    }
  },
  "metadata": {
    "success_rate": 1,
    "processing_time_ms": 72329,
    "scraper_version": "unified-firecrawl-v1.0",
    "data_format": "legacy-compatible"
  },
  "stats": {
    "avg_bounty_value": 100,
    "median_bounty_value": 100,
    "top_organizations": [
      {
        "handle": "ZIO",
        "display_name": "ZIO",
        "url": "https://algora.io/ZIO/bounties?status=open",
        "bounty_count": 10,
        "total_value_usd": 1000,
        "bounties": [
          {
            "id": "ZIO#3789",
            "title": "Server option to auto generate HEAD routes",
            "amount_usd": 100,
            "url": "https://github.com/zio/zio-http/issues/3789",
            "status": "open",
            "tags": [
              "go"
            ],
            "created_at": "2025-11-19T20:15:17.508Z",
            "updated_at": "2025-11-19T20:15:17.508Z"
          },
          {
            "id": "ZIO#3792",
            "title": "`DatastarEvent` handler for low-level API",
            "amount_usd": 100,
            "url": "https://github.com/zio/zio-http/issues/3792",
            "status": "open",
            "tags": [
              "go"
            ],
            "created_at": "2025-11-19T20:15:17.639Z",
            "updated_at": "2025-11-19T20:15:17.639Z"
          },
          {
            "id": "ZIO#3791",
            "title": "Read signals from query params to case class",
            "amount_usd": 100,
            "url": "https://github.com/zio/zio-http/issues/3791",
            "status": "open",
            "tags": [],
            "created_at": "2025-11-19T20:15:17.792Z",
            "updated_at": "2025-11-19T20:15:17.792Z"
          },
          {
            "id": "ZIO#3793",
            "title": "Datastar migration for 1.0.0 RC6",
            "amount_usd": 100,
            "url": "https://github.com/zio/zio-http/issues/3793",
            "status": "open",
            "tags": [],
            "created_at": "2025-11-19T20:15:17.993Z",
            "updated_at": "2025-11-19T20:15:17.993Z"
          },
          {
            "id": "ZIO#3794",
            "title": "Add constructors for CDN script elements and templates for datastart SSR pages",
            "amount_usd": 100,
            "url": "https://github.com/zio/zio-http/issues/3794",
            "status": "open",
            "tags": [],
            "created_at": "2025-11-19T20:15:18.252Z",
            "updated_at": "2025-11-19T20:15:18.252Z"
          },
          {
            "id": "ZIO#3779",
            "title": "Fix bug in JS HTTP Client not reading full response body",
            "amount_usd": 100,
            "url": "https://github.com/zio/zio-http/issues/3779",
            "status": "open",
            "tags": [],
            "created_at": "2025-11-19T20:15:18.405Z",
            "updated_at": "2025-11-19T20:15:18.405Z"
          },
          {
            "id": "ZIO#3697",
            "title": "Datastar requests from Endpoint",
            "amount_usd": 100,
            "url": "https://github.com/zio/zio-http/issues/3697",
            "status": "open",
            "tags": [],
            "created_at": "2025-11-19T20:15:18.559Z",
            "updated_at": "2025-11-19T20:15:18.559Z"
          },
          {
            "id": "ZIO#709",
            "title": "Support Http Range header on request for Files",
            "amount_usd": 100,
            "url": "https://github.com/zio/zio-http/issues/709",
            "status": "open",
            "tags": [],
            "created_at": "2025-11-19T20:15:18.691Z",
            "updated_at": "2025-11-19T20:15:18.691Z"
          },
          {
            "id": "ZIO#3472",
            "title": "Split into multiple modules",
            "amount_usd": 100,
            "url": "https://github.com/zio/zio-http/issues/3472",
            "status": "open",
            "tags": [],
            "created_at": "2025-11-19T20:15:18.903Z",
            "updated_at": "2025-11-19T20:15:18.903Z"
          },
          {
            "id": "ZIO#9810",
            "title": "ZStreams buffer(1) is buffering 2.",
            "amount_usd": 100,
            "url": "https://github.com/zio/zio/issues/9810",
            "status": "open",
            "tags": [],
            "created_at": "2025-11-19T20:15:19.047Z",
            "updated_at": "2025-11-19T20:15:19.047Z"
          }
        ],
        "last_updated": "2025-11-19T20:16:06.635Z",
        "scrape_duration_ms": 0
      },
      {
        "handle": "tscircuit",
        "display_name": "Tscircuit",
        "url": "https://algora.io/tscircuit/bounties?status=open",
        "bounty_count": 10,
        "total_value_usd": 1000,
        "bounties": [
          {
            "id": "tscircuit#1130",
            "title": "Change of color on hover for traces are missing",
            "amount_usd": 100,
            "url": "https://github.com/tscircuit/tscircuit/issues/1130",
            "status": "open",
            "tags": [
              "go"
            ],
            "created_at": "2025-11-19T20:15:17.670Z",
            "updated_at": "2025-11-19T20:15:17.670Z"
          },
          {
            "id": "tscircuit#83",
            "title": "In the case of multiple overlaps on a parallel line, choose to offset to minimize crossings",
            "amount_usd": 100,
            "url": "https://github.com/tscircuit/schematic-trace-solver/issues/83",
            "status": "open",
            "tags": [],
            "created_at": "2025-11-19T20:15:17.850Z",
            "updated_at": "2025-11-19T20:15:17.850Z"
          },
          {
            "id": "tscircuit#534",
            "title": "Texture Support (PCB should have texture on box)",
            "amount_usd": 100,
            "url": "https://github.com/tscircuit/3d-viewer/issues/534",
            "status": "open",
            "tags": [],
            "created_at": "2025-11-19T20:15:18.073Z",
            "updated_at": "2025-11-19T20:15:18.073Z"
          },
          {
            "id": "tscircuit#419",
            "title": "Texture Support (PCB should have texture on box)",
            "amount_usd": 100,
            "url": "https://github.com/tscircuit/3d-viewer/issues/534",
            "status": "open",
            "tags": [],
            "created_at": "2025-11-19T20:15:18.181Z",
            "updated_at": "2025-11-19T20:15:18.181Z"
          },
          {
            "id": "tscircuit#1081",
            "title": "Make sure kicad component components create courtyards",
            "amount_usd": 100,
            "url": "https://github.com/tscircuit/tscircuit/issues/1081",
            "status": "open",
            "tags": [],
            "created_at": "2025-11-19T20:15:18.380Z",
            "updated_at": "2025-11-19T20:15:18.380Z"
          },
          {
            "id": "tscircuit#386",
            "title": "Add support for qfn32",
            "amount_usd": 100,
            "url": "https://github.com/tscircuit/jscad-electronics/issues/139",
            "status": "open",
            "tags": [],
            "created_at": "2025-11-19T20:15:18.683Z",
            "updated_at": "2025-11-19T20:15:18.683Z"
          },
          {
            "id": "tscircuit#1498",
            "title": "Bug schematic traces with the same net name jumpeing to eachother ",
            "amount_usd": 100,
            "url": "https://github.com/tscircuit/core/issues/1498",
            "status": "open",
            "tags": [],
            "created_at": "2025-11-19T20:15:18.856Z",
            "updated_at": "2025-11-19T20:15:18.856Z"
          },
          {
            "id": "tscircuit#79",
            "title": "Fix extra net label in repro61, or remove trace",
            "amount_usd": 100,
            "url": "https://github.com/tscircuit/schematic-trace-solver/issues/79",
            "status": "open",
            "tags": [],
            "created_at": "2025-11-19T20:15:19.017Z",
            "updated_at": "2025-11-19T20:15:19.017Z"
          },
          {
            "id": "tscircuit#78",
            "title": "Fix extra trace lines in post-processing step",
            "amount_usd": 100,
            "url": "https://github.com/tscircuit/schematic-trace-solver/issues/78",
            "status": "open",
            "tags": [],
            "created_at": "2025-11-19T20:15:19.150Z",
            "updated_at": "2025-11-19T20:15:19.150Z"
          },
          {
            "id": "tscircuit#176",
            "title": "Proposal: Add SparkFun MicroMod STM32 Processor (STM32F405)",
            "amount_usd": 100,
            "url": "https://github.com/tscircuit/sparkfun-boards/issues/176",
            "status": "open",
            "tags": [],
            "created_at": "2025-11-19T20:15:19.312Z",
            "updated_at": "2025-11-19T20:15:19.312Z"
          }
        ],
        "last_updated": "2025-11-19T20:16:06.636Z",
        "scrape_duration_ms": 0
      },
      {
        "handle": "cal",
        "display_name": "Cal",
        "url": "https://algora.io/cal/bounties?status=open",
        "bounty_count": 10,
        "total_value_usd": 1000,
        "bounties": [
          {
            "id": "cal#23104",
            "title": "Local dev crazy slow",
            "amount_usd": 100,
            "url": "https://github.com/calcom/cal.com/issues/23104",
            "status": "open",
            "tags": [
              "go"
            ],
            "created_at": "2025-11-19T20:15:20.802Z",
            "updated_at": "2025-11-19T20:15:20.802Z"
          },
          {
            "id": "cal#9485",
            "title": "CalDAV integration with Fastmail is generating duplicate, erroneous invitation emails.",
            "amount_usd": 100,
            "url": "https://github.com/calcom/cal.com/issues/9485",
            "status": "open",
            "tags": [],
            "created_at": "2025-11-19T20:15:20.990Z",
            "updated_at": "2025-11-19T20:15:20.990Z"
          },
          {
            "id": "cal#18947",
            "title": "[CAL-5091] additional settings: \"add team member as optional guest",
            "amount_usd": 100,
            "url": "https://github.com/calcom/cal.com/issues/18947",
            "status": "open",
            "tags": [],
            "created_at": "2025-11-19T20:15:21.144Z",
            "updated_at": "2025-11-19T20:15:21.144Z"
          },
          {
            "id": "cal#18992",
            "title": "[CAL-5107] add no-show to zapier (its a webhook only right now)",
            "amount_usd": 100,
            "url": "https://github.com/calcom/cal.com/issues/18992",
            "status": "open",
            "tags": [],
            "created_at": "2025-11-19T20:15:21.284Z",
            "updated_at": "2025-11-19T20:15:21.284Z"
          },
          {
            "id": "cal#18987",
            "title": "[CAL-5097] add the same \"booking questions\" to routing forms",
            "amount_usd": 100,
            "url": "https://github.com/calcom/cal.com/issues/18987",
            "status": "open",
            "tags": [],
            "created_at": "2025-11-19T20:15:21.433Z",
            "updated_at": "2025-11-19T20:15:21.433Z"
          },
          {
            "id": "cal#16797",
            "title": "Native Pipedrive integration",
            "amount_usd": 100,
            "url": "https://github.com/calcom/cal.com/issues/16797",
            "status": "open",
            "tags": [],
            "created_at": "2025-11-19T20:15:21.590Z",
            "updated_at": "2025-11-19T20:15:21.590Z"
          },
          {
            "id": "cal#16651",
            "title": "[CAL-4716] Missing Notifications for Events",
            "amount_usd": 100,
            "url": "https://github.com/calcom/cal.com/issues/16651",
            "status": "open",
            "tags": [],
            "created_at": "2025-11-19T20:15:21.730Z",
            "updated_at": "2025-11-19T20:15:21.730Z"
          },
          {
            "id": "cal#8123",
            "title": "[CAL-1425] Exchange on Premise 2016",
            "amount_usd": 100,
            "url": "https://github.com/calcom/cal.com/issues/8123",
            "status": "open",
            "tags": [],
            "created_at": "2025-11-19T20:15:21.916Z",
            "updated_at": "2025-11-19T20:15:21.916Z"
          },
          {
            "id": "cal#16378",
            "title": "[CAL-4531] Take into account guest's availability when rescheduling",
            "amount_usd": 100,
            "url": "https://github.com/calcom/cal.com/issues/16378",
            "status": "open",
            "tags": [],
            "created_at": "2025-11-19T20:15:22.087Z",
            "updated_at": "2025-11-19T20:15:22.087Z"
          },
          {
            "id": "cal#13532",
            "title": "[CAL-3076] allow emails and invite people to a team event-type directly from \"assignment\" if not in team yet",
            "amount_usd": 100,
            "url": "https://github.com/calcom/cal.com/issues/13532",
            "status": "open",
            "tags": [],
            "created_at": "2025-11-19T20:15:22.266Z",
            "updated_at": "2025-11-19T20:15:22.266Z"
          }
        ],
        "last_updated": "2025-11-19T20:16:06.636Z",
        "scrape_duration_ms": 0
      },
      {
        "handle": "zio",
        "display_name": "Zio",
        "url": "https://algora.io/zio/bounties?status=open",
        "bounty_count": 10,
        "total_value_usd": 1000,
        "bounties": [
          {
            "id": "zio#3789",
            "title": "Server option to auto generate HEAD routes",
            "amount_usd": 100,
            "url": "https://github.com/zio/zio-http/issues/3789",
            "status": "open",
            "tags": [
              "go"
            ],
            "created_at": "2025-11-19T20:15:30.866Z",
            "updated_at": "2025-11-19T20:15:30.866Z"
          },
          {
            "id": "zio#3792",
            "title": "`DatastarEvent` handler for low-level API",
            "amount_usd": 100,
            "url": "https://github.com/zio/zio-http/issues/3792",
            "status": "open",
            "tags": [
              "go"
            ],
            "created_at": "2025-11-19T20:15:30.891Z",
            "updated_at": "2025-11-19T20:15:30.891Z"
          },
          {
            "id": "zio#3791",
            "title": "Read signals from query params to case class",
            "amount_usd": 100,
            "url": "https://github.com/zio/zio-http/issues/3791",
            "status": "open",
            "tags": [],
            "created_at": "2025-11-19T20:15:30.915Z",
            "updated_at": "2025-11-19T20:15:30.915Z"
          },
          {
            "id": "zio#3793",
            "title": "Datastar migration for 1.0.0 RC6",
            "amount_usd": 100,
            "url": "https://github.com/zio/zio-http/issues/3793",
            "status": "open",
            "tags": [],
            "created_at": "2025-11-19T20:15:30.940Z",
            "updated_at": "2025-11-19T20:15:30.940Z"
          },
          {
            "id": "zio#3794",
            "title": "Add constructors for CDN script elements and templates for datastart SSR pages",
            "amount_usd": 100,
            "url": "https://github.com/zio/zio-http/issues/3794",
            "status": "open",
            "tags": [],
            "created_at": "2025-11-19T20:15:30.965Z",
            "updated_at": "2025-11-19T20:15:30.965Z"
          },
          {
            "id": "zio#3779",
            "title": "Fix bug in JS HTTP Client not reading full response body",
            "amount_usd": 100,
            "url": "https://github.com/zio/zio-http/issues/3779",
            "status": "open",
            "tags": [],
            "created_at": "2025-11-19T20:15:30.990Z",
            "updated_at": "2025-11-19T20:15:30.990Z"
          },
          {
            "id": "zio#3697",
            "title": "Datastar requests from Endpoint",
            "amount_usd": 100,
            "url": "https://github.com/zio/zio-http/issues/3697",
            "status": "open",
            "tags": [],
            "created_at": "2025-11-19T20:15:31.014Z",
            "updated_at": "2025-11-19T20:15:31.014Z"
          },
          {
            "id": "zio#709",
            "title": "Support Http Range header on request for Files",
            "amount_usd": 100,
            "url": "https://github.com/zio/zio-http/issues/709",
            "status": "open",
            "tags": [],
            "created_at": "2025-11-19T20:15:31.039Z",
            "updated_at": "2025-11-19T20:15:31.039Z"
          },
          {
            "id": "zio#3472",
            "title": "Split into multiple modules",
            "amount_usd": 100,
            "url": "https://github.com/zio/zio-http/issues/3472",
            "status": "open",
            "tags": [],
            "created_at": "2025-11-19T20:15:31.064Z",
            "updated_at": "2025-11-19T20:15:31.064Z"
          },
          {
            "id": "zio#9810",
            "title": "ZStreams buffer(1) is buffering 2.",
            "amount_usd": 100,
            "url": "https://github.com/zio/zio/issues/9810",
            "status": "open",
            "tags": [],
            "created_at": "2025-11-19T20:15:31.089Z",
            "updated_at": "2025-11-19T20:15:31.089Z"
          }
        ],
        "last_updated": "2025-11-19T20:16:06.636Z",
        "scrape_duration_ms": 0
      },
      {
        "handle": "projectdiscovery",
        "display_name": "Projectdiscovery",
        "url": "https://algora.io/projectdiscovery/bounties?status=open",
        "bounty_count": 8,
        "total_value_usd": 800,
        "bounties": [
          {
            "id": "projectdiscovery#13942",
            "title": "Issue #13942",
            "amount_usd": 100,
            "url": "github.com/projectdiscovery/nuclei-templates/issues/13942",
            "status": "open",
            "tags": [
              "go"
            ],
            "created_at": "2025-11-19T20:15:56.363Z",
            "updated_at": "2025-11-19T20:15:56.363Z"
          },
          {
            "id": "projectdiscovery#13942",
            "title": "Issue #13942",
            "amount_usd": 100,
            "url": "github.com/projectdiscovery/nuclei-templates/issues/13942",
            "status": "open",
            "tags": [
              "go"
            ],
            "created_at": "2025-11-19T20:15:56.387Z",
            "updated_at": "2025-11-19T20:15:56.387Z"
          },
          {
            "id": "projectdiscovery#13933",
            "title": "Issue #13933",
            "amount_usd": 100,
            "url": "github.com/projectdiscovery/nuclei-templates/issues/13933",
            "status": "open",
            "tags": [],
            "created_at": "2025-11-19T20:15:56.411Z",
            "updated_at": "2025-11-19T20:15:56.411Z"
          },
          {
            "id": "projectdiscovery#13923",
            "title": "Issue #13923",
            "amount_usd": 100,
            "url": "github.com/projectdiscovery/nuclei-templates/issues/13923",
            "status": "open",
            "tags": [],
            "created_at": "2025-11-19T20:15:56.442Z",
            "updated_at": "2025-11-19T20:15:56.442Z"
          },
          {
            "id": "projectdiscovery#13915",
            "title": "Issue #13915",
            "amount_usd": 100,
            "url": "github.com/projectdiscovery/nuclei-templates/issues/13915",
            "status": "open",
            "tags": [],
            "created_at": "2025-11-19T20:15:56.466Z",
            "updated_at": "2025-11-19T20:15:56.466Z"
          },
          {
            "id": "projectdiscovery#13886",
            "title": "Issue #13886",
            "amount_usd": 100,
            "url": "github.com/projectdiscovery/nuclei-templates/issues/13886",
            "status": "open",
            "tags": [],
            "created_at": "2025-11-19T20:15:56.514Z",
            "updated_at": "2025-11-19T20:15:56.514Z"
          },
          {
            "id": "projectdiscovery#13820",
            "title": "Issue #13820",
            "amount_usd": 100,
            "url": "github.com/projectdiscovery/nuclei-templates/issues/13820",
            "status": "open",
            "tags": [],
            "created_at": "2025-11-19T20:15:56.538Z",
            "updated_at": "2025-11-19T20:15:56.538Z"
          },
          {
            "id": "projectdiscovery#13724",
            "title": "Issue #13724",
            "amount_usd": 100,
            "url": "github.com/projectdiscovery/nuclei-templates/issues/13724",
            "status": "open",
            "tags": [],
            "created_at": "2025-11-19T20:15:56.586Z",
            "updated_at": "2025-11-19T20:15:56.586Z"
          }
        ],
        "last_updated": "2025-11-19T20:16:06.636Z",
        "scrape_duration_ms": 0
      },
      {
        "handle": "mudlet",
        "display_name": "Mudlet",
        "url": "https://algora.io/mudlet/bounties?status=open",
        "bounty_count": 6,
        "total_value_usd": 600,
        "bounties": [
          {
            "id": "mudlet#8030",
            "title": "Split Mudlet up into `libmudlet` and a Qt front-end",
            "amount_usd": 100,
            "url": "https://github.com/Mudlet/Mudlet/issues/8030",
            "status": "open",
            "tags": [
              "go"
            ],
            "created_at": "2025-11-19T20:15:17.762Z",
            "updated_at": "2025-11-19T20:15:17.762Z"
          },
          {
            "id": "mudlet#3172",
            "title": "generic mapper: add video walkthrough on how to set it up",
            "amount_usd": 100,
            "url": "https://github.com/Mudlet/Mudlet/issues/3172",
            "status": "open",
            "tags": [
              "go"
            ],
            "created_at": "2025-11-19T20:15:17.951Z",
            "updated_at": "2025-11-19T20:15:17.951Z"
          },
          {
            "id": "mudlet#7126",
            "title": "Implement sentry.io's Qt SDK for crash reporting",
            "amount_usd": 100,
            "url": "https://github.com/Mudlet/Mudlet/issues/7126",
            "status": "open",
            "tags": [],
            "created_at": "2025-11-19T20:15:18.099Z",
            "updated_at": "2025-11-19T20:15:18.099Z"
          },
          {
            "id": "mudlet#689",
            "title": "Support telnet:// links",
            "amount_usd": 100,
            "url": "https://github.com/Mudlet/Mudlet/issues/689",
            "status": "open",
            "tags": [],
            "created_at": "2025-11-19T20:15:18.252Z",
            "updated_at": "2025-11-19T20:15:18.252Z"
          },
          {
            "id": "mudlet#707",
            "title": "Undo/redo support in editor",
            "amount_usd": 100,
            "url": "https://github.com/Mudlet/Mudlet/issues/707",
            "status": "open",
            "tags": [],
            "created_at": "2025-11-19T20:15:18.445Z",
            "updated_at": "2025-11-19T20:15:18.445Z"
          },
          {
            "id": "mudlet#5310",
            "title": "Autocomplete steals window focus, prevents further typing",
            "amount_usd": 100,
            "url": "https://github.com/Mudlet/Mudlet/issues/5310",
            "status": "open",
            "tags": [],
            "created_at": "2025-11-19T20:15:18.619Z",
            "updated_at": "2025-11-19T20:15:18.619Z"
          }
        ],
        "last_updated": "2025-11-19T20:16:06.635Z",
        "scrape_duration_ms": 0
      },
      {
        "handle": "Mudlet",
        "display_name": "Mudlet",
        "url": "https://algora.io/Mudlet/bounties?status=open",
        "bounty_count": 6,
        "total_value_usd": 600,
        "bounties": [
          {
            "id": "Mudlet#8030",
            "title": "Issue #8030",
            "amount_usd": 100,
            "url": "github.com/Mudlet/Mudlet/issues/8030",
            "status": "open",
            "tags": [
              "go"
            ],
            "created_at": "2025-11-19T20:15:34.852Z",
            "updated_at": "2025-11-19T20:15:34.852Z"
          },
          {
            "id": "Mudlet#3172",
            "title": "Issue #3172",
            "amount_usd": 100,
            "url": "github.com/Mudlet/Mudlet/issues/3172",
            "status": "open",
            "tags": [
              "go"
            ],
            "created_at": "2025-11-19T20:15:34.876Z",
            "updated_at": "2025-11-19T20:15:34.876Z"
          },
          {
            "id": "Mudlet#7126",
            "title": "Issue #7126",
            "amount_usd": 100,
            "url": "github.com/Mudlet/Mudlet/issues/7126",
            "status": "open",
            "tags": [],
            "created_at": "2025-11-19T20:15:34.900Z",
            "updated_at": "2025-11-19T20:15:34.900Z"
          },
          {
            "id": "Mudlet#689",
            "title": "Issue #689",
            "amount_usd": 100,
            "url": "github.com/Mudlet/Mudlet/issues/689",
            "status": "open",
            "tags": [],
            "created_at": "2025-11-19T20:15:34.925Z",
            "updated_at": "2025-11-19T20:15:34.925Z"
          },
          {
            "id": "Mudlet#707",
            "title": "Issue #707",
            "amount_usd": 100,
            "url": "github.com/Mudlet/Mudlet/issues/707",
            "status": "open",
            "tags": [],
            "created_at": "2025-11-19T20:15:34.949Z",
            "updated_at": "2025-11-19T20:15:34.949Z"
          },
          {
            "id": "Mudlet#5310",
            "title": "Issue #5310",
            "amount_usd": 100,
            "url": "github.com/Mudlet/Mudlet/issues/5310",
            "status": "open",
            "tags": [],
            "created_at": "2025-11-19T20:15:34.974Z",
            "updated_at": "2025-11-19T20:15:34.974Z"
          }
        ],
        "last_updated": "2025-11-19T20:16:06.636Z",
        "scrape_duration_ms": 0
      },
      {
        "handle": "keephq",
        "display_name": "Keephq",
        "url": "https://algora.io/keephq/bounties?status=open",
        "bounty_count": 5,
        "total_value_usd": 500,
        "bounties": [
          {
            "id": "keephq#3960",
            "title": "[🔌 Provider]: Nagios Provider",
            "amount_usd": 100,
            "url": "https://github.com/keephq/keep/issues/3960",
            "status": "open",
            "tags": [
              "go"
            ],
            "created_at": "2025-11-19T20:15:28.482Z",
            "updated_at": "2025-11-19T20:15:28.482Z"
          },
          {
            "id": "keephq#3526",
            "title": "[🔌 Provider]: Solarwinds",
            "amount_usd": 100,
            "url": "https://github.com/keephq/keep/issues/3526",
            "status": "open",
            "tags": [],
            "created_at": "2025-11-19T20:15:28.643Z",
            "updated_at": "2025-11-19T20:15:28.643Z"
          },
          {
            "id": "keephq#3376",
            "title": "[➕ Feature]: Add a way to validate Keep workflows from CI",
            "amount_usd": 100,
            "url": "https://github.com/keephq/keep/issues/3376",
            "status": "open",
            "tags": [],
            "created_at": "2025-11-19T20:15:28.773Z",
            "updated_at": "2025-11-19T20:15:28.773Z"
          },
          {
            "id": "keephq#3379",
            "title": "[🔌 Provider]: ServiceNow pull activity from incidents into incidents",
            "amount_usd": 100,
            "url": "https://github.com/keephq/keep/issues/3379",
            "status": "open",
            "tags": [],
            "created_at": "2025-11-19T20:15:28.900Z",
            "updated_at": "2025-11-19T20:15:28.900Z"
          },
          {
            "id": "keephq#2112",
            "title": "[🔌 Provider]: SNMP provider",
            "amount_usd": 100,
            "url": "https://github.com/keephq/keep/issues/2112",
            "status": "open",
            "tags": [],
            "created_at": "2025-11-19T20:15:29.069Z",
            "updated_at": "2025-11-19T20:15:29.069Z"
          }
        ],
        "last_updated": "2025-11-19T20:16:06.636Z",
        "scrape_duration_ms": 0
      },
      {
        "handle": "activepieces",
        "display_name": "Activepieces",
        "url": "https://algora.io/activepieces/bounties?status=open",
        "bounty_count": 5,
        "total_value_usd": 500,
        "bounties": [
          {
            "id": "activepieces#9703",
            "title": "Issue #9703",
            "amount_usd": 100,
            "url": "github.com/activepieces/activepieces/issues/9703",
            "status": "open",
            "tags": [
              "go"
            ],
            "created_at": "2025-11-19T20:15:31.290Z",
            "updated_at": "2025-11-19T20:15:31.290Z"
          },
          {
            "id": "activepieces#8284",
            "title": "Issue #8284",
            "amount_usd": 100,
            "url": "github.com/activepieces/activepieces/issues/8284",
            "status": "open",
            "tags": [
              "go"
            ],
            "created_at": "2025-11-19T20:15:31.314Z",
            "updated_at": "2025-11-19T20:15:31.314Z"
          },
          {
            "id": "activepieces#8135",
            "title": "Issue #8135",
            "amount_usd": 100,
            "url": "github.com/activepieces/activepieces/issues/8135",
            "status": "open",
            "tags": [],
            "created_at": "2025-11-19T20:15:31.339Z",
            "updated_at": "2025-11-19T20:15:31.339Z"
          },
          {
            "id": "activepieces#8135",
            "title": "Issue #8135",
            "amount_usd": 100,
            "url": "github.com/activepieces/activepieces/issues/8135",
            "status": "open",
            "tags": [],
            "created_at": "2025-11-19T20:15:31.363Z",
            "updated_at": "2025-11-19T20:15:31.363Z"
          },
          {
            "id": "activepieces#8072",
            "title": "Issue #8072",
            "amount_usd": 100,
            "url": "github.com/activepieces/activepieces/issues/8072",
            "status": "open",
            "tags": [],
            "created_at": "2025-11-19T20:15:31.387Z",
            "updated_at": "2025-11-19T20:15:31.387Z"
          }
        ],
        "last_updated": "2025-11-19T20:16:06.636Z",
        "scrape_duration_ms": 0
      },
      {
        "handle": "qdrant",
        "display_name": "Qdrant",
        "url": "https://algora.io/qdrant/bounties?status=open",
        "bounty_count": 3,
        "total_value_usd": 300,
        "bounties": [
          {
            "id": "qdrant#3531",
            "title": "Issue #3531",
            "amount_usd": 100,
            "url": "github.com/qdrant/qdrant/issues/3531",
            "status": "open",
            "tags": [
              "go"
            ],
            "created_at": "2025-11-19T20:15:56.562Z",
            "updated_at": "2025-11-19T20:15:56.562Z"
          },
          {
            "id": "qdrant#3322",
            "title": "Issue #3322",
            "amount_usd": 100,
            "url": "github.com/qdrant/qdrant/issues/3322",
            "status": "open",
            "tags": [],
            "created_at": "2025-11-19T20:15:56.609Z",
            "updated_at": "2025-11-19T20:15:56.609Z"
          },
          {
            "id": "qdrant#3321",
            "title": "Issue #3321",
            "amount_usd": 100,
            "url": "github.com/qdrant/qdrant/issues/3321",
            "status": "open",
            "tags": [],
            "created_at": "2025-11-19T20:15:56.634Z",
            "updated_at": "2025-11-19T20:15:56.634Z"
          }
        ],
        "last_updated": "2025-11-19T20:16:06.636Z",
        "scrape_duration_ms": 0
      }
    ]
  }
}