{
  "updated_at": "2025-09-21T20:45:37.993Z",
  "version": "1.0.0",
  "organizations": [
    {
      "handle": "ZIO",
      "display_name": "ZIO",
      "url": "https://algora.io/ZIO/bounties?status=open",
      "active": true,
      "scrape_interval": 900
    },
    {
      "handle": "cal",
      "display_name": "Cal.com",
      "url": "https://algora.io/cal/bounties?status=open",
      "active": true,
      "scrape_interval": 900
    },
    {
      "handle": "calcom",
      "display_name": "Cal.com",
      "url": "https://algora.io/calcom/bounties?status=open",
      "active": true,
      "scrape_interval": 900
    },
    {
      "handle": "twenty",
      "display_name": "Twenty",
      "url": "https://algora.io/twenty/bounties?status=open",
      "active": true,
      "scrape_interval": 900
    },
    {
      "handle": "twentyhq",
      "display_name": "Twenty HQ",
      "url": "https://algora.io/twentyhq/bounties?status=open",
      "active": true,
      "scrape_interval": 900
    },
    {
      "handle": "activepieces",
      "display_name": "Activepieces",
      "url": "https://algora.io/activepieces/bounties?status=open",
      "active": true,
      "scrape_interval": 900
    },
    {
      "handle": "tscircuit",
      "display_name": "tscircuit",
      "url": "https://algora.io/tscircuit/bounties?status=open",
      "active": true,
      "scrape_interval": 900
    },
    {
      "handle": "projectdiscovery",
      "display_name": "ProjectDiscovery",
      "url": "https://algora.io/projectdiscovery/bounties?status=open",
      "active": true,
      "scrape_interval": 900
    },
    {
      "handle": "triggerdotdev",
      "display_name": "Trigger.dev",
      "url": "https://algora.io/triggerdotdev/bounties?status=open",
      "active": true,
      "scrape_interval": 900
    },
    {
      "handle": "highlight",
      "display_name": "Highlight",
      "url": "https://algora.io/highlight/bounties?status=open",
      "active": true,
      "scrape_interval": 900
    },
    {
      "handle": "remotion",
      "display_name": "Remotion",
      "url": "https://algora.io/remotion/bounties?status=open",
      "active": true,
      "scrape_interval": 900
    },
    {
      "handle": "remotion-dev",
      "display_name": "Remotion Dev",
      "url": "https://algora.io/remotion-dev/bounties?status=open",
      "active": true,
      "scrape_interval": 900
    },
    {
      "handle": "documenso",
      "display_name": "Documenso",
      "url": "https://algora.io/documenso/bounties?status=open",
      "active": true,
      "scrape_interval": 900
    },
    {
      "handle": "coollabsio",
      "display_name": "Coolify",
      "url": "https://algora.io/coollabsio/bounties?status=open",
      "active": true,
      "scrape_interval": 900
    },
    {
      "handle": "traceloop",
      "display_name": "Traceloop",
      "url": "https://algora.io/traceloop/bounties?status=open",
      "active": true,
      "scrape_interval": 900
    },
    {
      "handle": "algora-io",
      "display_name": "Algora",
      "url": "https://algora.io/algora-io/bounties?status=open",
      "active": true,
      "scrape_interval": 900
    },
    {
      "handle": "mudlet",
      "display_name": "Mudlet",
      "url": "https://algora.io/mudlet/bounties?status=open",
      "active": true,
      "scrape_interval": 900
    }
  ]
}